[
    {
        "Tema": "Python para leigos",
        "Data": "20/10/2025",
        "Local": "teste",
        "Capacidade_max": 120,
        "Numero_inscritos": 0,
        "Categoria": "Teste",
        "Preço ingresso": 120.0
    },
    {
        "Tema": "Python para leigos",
        "Data": "20/10/2025",
        "Local": "teste",
        "Capacidade_max": 120,
        "Numero_inscritos": 0,
        "Categoria": "Teste",
        "Preço ingresso": 120.0
    },
    {
        "Tema": "Python para leigos",
        "Data": "20/10/2025",
        "Local": "teste",
        "Capacidade_max": 120,
        "Numero_inscritos": 0,
        "Categoria": "Teste",
        "Preço ingresso": 120.0
    },
    {
        "Tema": "Bartosz",
        "Data": "29/12/2025",
        "Local": "recife",
        "Capacidade_max": 0,
        "Numero_inscritos": 0,
        "Categoria": "tech",
        "Preço ingresso": 0.0
    },
    {
        "Tema": "aniv camila",
        "Data": "02/04/2026",
        "Local": "Recife",
        "Capacidade_max": 120,
        "Numero_inscritos": 0,
        "Categoria": "Tech",
        "Preço ingresso": 0.0
    },
    {
        "Tema": "Aniv. Junior",
        "Data": "30/10/2025",
        "Local": "Casa Recife",
        "Capacidade_max": 120,
        "Numero_inscritos": 0,
        "Categoria": "Marketing",
        "Preço ingresso": 0.0
    },
    {
        "Tema": "Aniversário Bartosz",
        "Data": "29/12/2025",
        "Local": "Iputinga",
        "Capacidade_max": 120,
        "Numero_inscritos": 0,
        "Categoria": "Festa",
        "Preço ingresso": 0.0
    },
    {
        "Tema": "teste001",
        "Data": "10/10/2025",
        "Local": "teste",
        "Capacidade_max": 10,
        "Numero_inscritos": 0,
        "Categoria": "saude",
        "Preço ingresso": 10.0
    },
    {
        "Tema": "teste003",
        "Data": "02/01/2026",
        "Local": "Petrolina",
        "Capacidade_max": 20,
        "Numero_inscritos": 0,
        "Categoria": "tech",
        "Preço ingresso": 312.0
    },
    {
        "Tema": "teste005",
        "Data": "31/10/2027",
        "Local": "Paulista",
        "Capacidade_max": 80,
        "Numero_inscritos": 0,
        "Categoria": "marketing",
        "Preço ingresso": 0.0
    },
    {
        "Tema": "teste777",
        "Data": "20/10/2028",
        "Local": "Recife",
        "Capacidade_max": 55,
        "Numero_inscritos": 0,
        "Categoria": "tech",
        "Preço ingresso": 40.0
    }
]